udacity_chiron/__init__.py
udacity_chiron/__main__.py
udacity_chiron/chiron.py
udacity_chiron/sessionbuilder.py
udacity_chiron/udacity.py
udacity_chiron/uploadcallbacks.py
udacity_chiron-0.1.1.dist-info/DESCRIPTION.rst
udacity_chiron-0.1.1.dist-info/METADATA
udacity_chiron-0.1.1.dist-info/RECORD
udacity_chiron-0.1.1.dist-info/WHEEL
udacity_chiron-0.1.1.dist-info/entry_points.txt
udacity_chiron-0.1.1.dist-info/metadata.json
udacity_chiron-0.1.1.dist-info/top_level.txt
