Metadata-Version: 2.0
Name: udacity-chiron
Version: 0.1.1
Summary: CLI tool for interacting with Chiron feedback service.
Home-page: http://github.com/udacity/udacity-chiron
Author: S. Charles Brubaker
Author-email: cb@udacity.com
License: MIT
Keywords: Udacity
Platform: UNKNOWN
Requires-Dist: future
Requires-Dist: requests (>=2.2.1)
Requires-Dist: requests-toolbelt (>=0.7.0)
